kesha/__init__.py
kesha/apps.py
kesha/migrations/0001_initial.py
kesha/migrations/0002_booking_document.py
kesha/migrations/0003_auto_20210421_1552.py
kesha/migrations/0004_auto_20210425_0332.py
kesha/migrations/0005_parent_parent.py
kesha/migrations/0006_auto_20210428_1530.py
kesha/migrations/__init__.py
kesha/models.py
django_kesha-0.1.2.dist-info/WHEEL
django_kesha-0.1.2.dist-info/METADATA
django_kesha-0.1.2.dist-info/RECORD
