Metadata-Version: 2.1
Name: django-kesha
Version: 0.1.2
Summary: Accounting Helper Django App
Home-page: https://github.com/olf42/django-kesha
License: GPL-3.0
Author: Florian Rämisch
Author-email: olf@subsignal.org
Requires-Python: >=3.7,<4.0
Classifier: License :: OSI Approved :: GNU General Public License v3 (GPLv3)
Classifier: Programming Language :: Python :: 3
Classifier: Programming Language :: Python :: 3.7
Classifier: Programming Language :: Python :: 3.8
Classifier: Programming Language :: Python :: 3.9
Requires-Dist: Django (>=3.2,<4.0)
Requires-Dist: PyYAML (>=5.4.1,<6.0.0)
Requires-Dist: django-doma (>=0.2.1,<0.3.0)
Requires-Dist: django-money (>=1.3.1,<2.0.0)
Project-URL: Repository, https://github.com/olf42/django-kesha
